elasticsearchlib/__init__.py
elasticsearchlib/elastic_mappings.py
elasticsearchlib/elastic_queries.py
elasticsearchlib/elasticsearchlib.py
easierai_elasticsearchlib-1.3.8.dist-info/LICENSE
easierai_elasticsearchlib-1.3.8.dist-info/METADATA
easierai_elasticsearchlib-1.3.8.dist-info/WHEEL
easierai_elasticsearchlib-1.3.8.dist-info/top_level.txt
easierai_elasticsearchlib-1.3.8.dist-info/RECORD
