Metadata-Version: 2.1
Name: easierai-elasticsearchlib
Version: 1.3.8
Summary: This library manages the communication between python programs and elasticsearch database
Home-page: https://gitlab.atosresearch.eu/ari/ioe-ai/data-elasticsearch_python
Author: IoE Lab
Author-email: juan.carrascoa@atos.net
License: ATOS
Platform: UNKNOWN
Requires-Dist: elasticsearch (==7.1.0)
Requires-Dist: pydash
Requires-Dist: certifi
Requires-Dist: requests
